authorizeme.py
authorizeme-0.2.1.dist-info/DESCRIPTION.rst
authorizeme-0.2.1.dist-info/METADATA
authorizeme-0.2.1.dist-info/metadata.json
authorizeme-0.2.1.dist-info/RECORD
authorizeme-0.2.1.dist-info/top_level.txt
authorizeme-0.2.1.dist-info/WHEEL
