Metadata-Version: 2.0
Name: authorizeme
Version: 0.2.1
Summary: Authorization library for Python
Home-page: https://github.com/antonev/authorizeme
Author: Anton Evdokimov
Author-email: antonevv@gmail.com
License: MIT
Platform: any
Classifier: Development Status :: 4 - Beta
Classifier: Intended Audience :: Developers
Classifier: License :: OSI Approved :: MIT License
Classifier: Operating System :: OS Independent
Classifier: Programming Language :: Python
Classifier: Programming Language :: Python :: 2
Classifier: Programming Language :: Python :: 2.7
Classifier: Programming Language :: Python :: 3
Classifier: Programming Language :: Python :: 3.4
